{"cameraMode":{"drawMode":0,"name":"Shaded","section":"Shading Mode"},"sceneLighting":true,"audioPlay":false,"sceneViewState":{"m_AlwaysRefresh":false,"showFog":true,"showSkybox":true,"showFlares":true,"showImageEffects":true,"showParticleSystems":true,"showVisualEffectGraphs":true,"m_FxEnabled":true},"in2DMode":false,"pivot":{"x":-6.355008125305176,"y":-1.9760422706604005,"z":-4.491684913635254},"rotation":{"x":-0.06772900372743607,"y":0.9128397703170776,"z":-0.16923275589942933,"w":-0.3653401732444763},"size":10.0,"orthographic":false}